tm1637/__init__.py
tm1637/tm1637.py
python_tm1637-2.0.1.dist-info/METADATA
python_tm1637-2.0.1.dist-info/WHEEL
python_tm1637-2.0.1.dist-info/licenses/LICENSE
python_tm1637-2.0.1.dist-info/RECORD
