Metadata-Version: 2.4
Name: python-tm1637
Version: 2.0.1
Summary: Library for TM1637-based LED display modules
Project-URL: homepage, https://github.com/pantheraleo-7/tm1637
Author: Asadullah Shaikh
License-File: LICENSE
Keywords: 7,display,gpiod,led,segment,tm1637
Classifier: Development Status :: 5 - Production/Stable
Classifier: Intended Audience :: Developers
Classifier: Intended Audience :: Education
Classifier: License :: OSI Approved :: MIT License
Classifier: Operating System :: POSIX :: Linux
Classifier: Programming Language :: Python :: 3
Classifier: Topic :: Education
Classifier: Topic :: Software Development :: Embedded Systems
Classifier: Topic :: Software Development :: Libraries :: Python Modules
Classifier: Topic :: System :: Hardware :: Hardware Drivers
Requires-Python: >=3.9
Requires-Dist: gpiod>=2.3.0
